extclass/__init__.py
extclass-1.0.0.dist-info/LICENSE
extclass-1.0.0.dist-info/METADATA
extclass-1.0.0.dist-info/WHEEL
extclass-1.0.0.dist-info/top_level.txt
extclass-1.0.0.dist-info/RECORD
