Metadata-Version: 2.1
Name: extclass
Version: 1.0.0
Summary: A Python approach for class extensions like C# and Kotlin
Home-page: https://github.com/wolray/extclass
Author: wolray
Author-email: wolray@foxmail.com
Classifier: Programming Language :: Python :: 3
Classifier: License :: OSI Approved :: MIT License
Classifier: Operating System :: OS Independent
Requires-Python: >=3.8
License-File: LICENSE
